claude_notify/__init__.py
claude_notify/cli.py
claude_notify/config.py
claude_notify/hook_handler.py
claude_notify/notifier.py
claude_notify/session_monitor.py
claude_notify-0.1.1.dist-info/licenses/LICENSE
claude_notify-0.1.1.dist-info/METADATA
claude_notify-0.1.1.dist-info/WHEEL
claude_notify-0.1.1.dist-info/entry_points.txt
claude_notify-0.1.1.dist-info/top_level.txt
claude_notify-0.1.1.dist-info/RECORD
