Metadata-Version: 2.4
Name: claude-notify
Version: 0.1.1
Summary: Cross-platform notification system for Claude Code hooks with intelligent project detection
Home-page: https://github.com/jamez01/claude-notify
Author: jamez01
Author-email: jamez01 <james@example.com>
License: MIT
Project-URL: Homepage, https://github.com/jamez01/claude-notify
Project-URL: Repository, https://github.com/jamez01/claude-notify.git
Project-URL: Issues, https://github.com/jamez01/claude-notify/issues
Keywords: claude,ai,notifications,hooks,cross-platform,desktop
Classifier: Development Status :: 4 - Beta
Classifier: Intended Audience :: Developers
Classifier: Topic :: Software Development
Classifier: Topic :: System :: Monitoring
Classifier: Topic :: Communications
Classifier: Programming Language :: Python :: 3
Classifier: Programming Language :: Python :: 3.7
Classifier: Programming Language :: Python :: 3.8
Classifier: Programming Language :: Python :: 3.9
Classifier: Programming Language :: Python :: 3.10
Classifier: Programming Language :: Python :: 3.11
Classifier: Programming Language :: Python :: 3.12
Classifier: License :: OSI Approved :: MIT License
Classifier: Operating System :: OS Independent
Classifier: Operating System :: MacOS
Classifier: Operating System :: Microsoft :: Windows
Classifier: Operating System :: POSIX :: Linux
Requires-Python: >=3.7
License-File: LICENSE
Requires-Dist: plyer>=2.1
Requires-Dist: click>=8.1.0
Requires-Dist: pyyaml>=6.0
Dynamic: author
Dynamic: home-page
Dynamic: license-file
Dynamic: requires-python
